<?xml version="1.0" encoding="ISO-8859-1"?>
<Racine xmlns:xsi="http://www.w3.org/2001/XMLSchema-instance">
<IdentificationFlux>
<APPLIEME>CRI</APPLIEME>
<NUMVERSIONAPPLIEME>6300</NUMVERSIONAPPLIEME>
<TYPEFLUX>I</TYPEFLUX>
<NATFLUX>D</NATFLUX>
<DTCREAFLUX>2022-03-23</DTCREAFLUX>
<HEUCREAFLUX>21:25:56.0000</HEUCREAFLUX>
<DTREF>2022-03-23</DTREF>
</IdentificationFlux>
<InfosFoyerRSA>
<IdentificationRSA>
<Organisme>
<FONORG>CAF</FONORG>
<NUMORG>771</NUMORG>
<MATRICULE>773617000000000</MATRICULE>
</Organisme>
<Partenaire>
<TYPEPARTE>CG  </TYPEPARTE>
<IDEPARTE>077</IDEPARTE>
</Partenaire>
<DemandeRSA>
<DTDEMRSA>2022-03-03</DTDEMRSA>
<NUMDEMRSA>01245011077</NUMDEMRSA>
</DemandeRSA>
</IdentificationRSA>
<Personne>
<Identification>
<QUAL>MR</QUAL>
<NOM>xxxxx</NOM>
<NOMNAI>xxxxx</NOMNAI>
<PRENOM>xxxxx</PRENOM>
<PRENOM2>xxxxx</PRENOM2>
<NOMCOMNAI>CROIX-DES-BOUQUETS</NOMCOMNAI>
<DTNAI>1996-11-12</DTNAI>
<TYPEDTNAI>N</TYPEDTNAI>
<NIR>1961199410118</NIR>
<TOPVALIEC>1</TOPVALIEC>
<SEXE>1</SEXE>
</Identification>
<DossierCAF>
<TOPRESPDOS>1</TOPRESPDOS>
<DDRATDOS>1996-11-12</DDRATDOS>
</DossierCAF>
<Prestations>
<NATPREST>PFA</NATPREST>
<ROLEPERS>DEM</ROLEPERS>
<TOPCHAPERS>0</TOPCHAPERS>
</Prestations>
<Prestations>
<NATPREST>RSA</NATPREST>
<ROLEPERS>DEM</ROLEPERS>
<TOPCHAPERS>0</TOPCHAPERS>
</Prestations>
<DossierPoleEmploi>
<IDASSEDIC>8133785W</IDASSEDIC>
</DossierPoleEmploi>
<Activite>
<REG>GE</REG>
<ACT>ADA</ACT>
<DDACT>2022-02-01</DDACT>
</Activite>
</Personne>
<DonneesAdministratives>
<SituationFamille>
<SITFAM>CEL</SITFAM>
<DDSITFAM>1996-11-12</DDSITFAM>
</SituationFamille>
<Adresse>
<TroncCommunAdresse>
<RGADR>01</RGADR>
<DTEMM>2021-11-16</DTEMM>
<PAYS>FRA</PAYS>
<TYPEADR>D</TYPEADR>
<ETATADR>CO</ETATADR>
</TroncCommunAdresse>
<AdresseDetailleeFrance>
<COMPLIDEADR>APPARTEMENT 113</COMPLIDEADR>
<COMPLADR></COMPLADR>
<NUMVOIE>18</NUMVOIE>
<LIBTYPEVOIE>COURS</LIBTYPEVOIE>
<NOMVOIE>DU DANUBE</NOMVOIE>
<LIEUDIST></LIEUDIST>
<NUMCOM>77449</NUMCOM>
<CODEPOS>77700</CODEPOS>
<NOMCOM>SERRIS</NOMCOM>
</AdresseDetailleeFrance>
</Adresse>
<Adresse>
<TroncCommunAdresse>
<RGADR>02</RGADR>
<DTEMM>2019-11-05</DTEMM>
<PAYS>FRA</PAYS>
<TYPEADR>D</TYPEADR>
<ETATADR>CO</ETATADR>
</TroncCommunAdresse>
<AdresseDetailleeFrance>
<COMPLIDEADR>APPARTEMENT 3217 BOITE 173</COMPLIDEADR>
<COMPLADR>RESIDENCE ALJT</COMPLADR>
<NUMVOIE>1</NUMVOIE>
<LIBTYPEVOIE>RUE</LIBTYPEVOIE>
<NOMVOIE>DE BRUXELLES</NOMVOIE>
<LIEUDIST></LIEUDIST>
<NUMCOM>77307</NUMCOM>
<CODEPOS>77144</CODEPOS>
<NOMCOM>MONTEVRAIN</NOMCOM>
</AdresseDetailleeFrance>
</Adresse>
</DonneesAdministratives>
<PrestationRSA>
<SituationDossierRSA>
</SituationDossierRSA>
<DetailDroitRSA>
<TroncCommunDroitRSA>
<TOPSANSDOMFIXE>0</TOPSANSDOMFIXE>
<ORIDEMRSA>DEM</ORIDEMRSA>
<DTORIDEMRSA>2022-03-03</DTORIDEMRSA>
</TroncCommunDroitRSA>
</DetailDroitRSA>
</PrestationRSA>
<Anomalie>
<LIBANO>DOSSIER 7736170 : AUCUN CAS DETECTE POUR TRAITER LE BLOC SITDOSRSA</LIBANO>
</Anomalie>
</InfosFoyerRSA>
<TransmissionFlux>
<NBTOTDOSRSATRANSMANO>00000001</NBTOTDOSRSATRANSMANO>
</TransmissionFlux>
</Racine>
